mazegym/__init__.py
mazegym/maze_gym_env.py
mazegym/register_env.py
mazegym-1.2.3.dist-info/licenses/LICENSE
mazegym-1.2.3.dist-info/METADATA
mazegym-1.2.3.dist-info/WHEEL
mazegym-1.2.3.dist-info/top_level.txt
mazegym-1.2.3.dist-info/RECORD
