Metadata-Version: 2.4
Name: mazegym
Version: 1.2.3
Summary: A Gymnasium environment for maze-based reinforcement learning
Author-email: Evaldas Visockas <developersediary@gmail.com>
License: GPL-3.0-or-later
Project-URL: Repository, https://github.com/EvalVis/MazeGym
Classifier: Programming Language :: Python :: 3
Classifier: License :: OSI Approved :: GNU General Public License v3 (GPLv3)
Classifier: Operating System :: OS Independent
Classifier: Topic :: Scientific/Engineering :: Artificial Intelligence
Requires-Python: >=3.8
License-File: LICENSE
Requires-Dist: numpy>=2.2.3
Requires-Dist: gymnasium>=1.0.0
Requires-Dist: matplotlib>=3.10.1
Requires-Dist: mazelib>=0.9.16
Provides-Extra: dev
Requires-Dist: pytest>=8.3.4; extra == "dev"
Dynamic: license-file
